qunet/__init__.py
qunet/batch.py
qunet/callback.py
qunet/config.py
qunet/data.py
qunet/ema.py
qunet/losses.py
qunet/modelstate.py
qunet/old.py
qunet/plots.py
qunet/trainer.py
qunet/utils.py
qunet/modules/__init__.py
qunet/modules/cnn.py
qunet/modules/cnn3D.py
qunet/modules/cnn_old.py
qunet/modules/gnn.py
qunet/modules/mlp.py
qunet/modules/points.py
qunet/modules/residual.py
qunet/modules/total.py
qunet/modules/transformer.py
qunet/modules/transformer_plot.py
qunet/modules/vit.py
qunet/optim/__init__.py
qunet/optim/adams.py
qunet/optim/lion.py
qunet/optim/scheduler.py
qunet/rl/__init__.py
qunet/rl/dqn.py
qunet/rl/memory_buffer.py
QuNet-0.0.190.dist-info/LICENSE
QuNet-0.0.190.dist-info/METADATA
QuNet-0.0.190.dist-info/WHEEL
QuNet-0.0.190.dist-info/top_level.txt
QuNet-0.0.190.dist-info/RECORD
