Metadata-Version: 2.1
Name: QuNet
Version: 0.0.190
Summary: Working with deep learning models
Home-page: https://github.com/QuDataAI/qunet
Author: synset
Author-email: steps137ai@gmail.com
License: UNKNOWN
Platform: UNKNOWN
Classifier: Programming Language :: Python :: 3
Classifier: License :: OSI Approved :: MIT License
Classifier: Operating System :: OS Independent
